FileOptimizer/__init__.py
FileOptimizer/__main__.py
FileOptimizer/extensions.py
FileOptimizer/main.py
FileOptimizerPy-1.1.1641.dist-info/LICENSE
FileOptimizerPy-1.1.1641.dist-info/METADATA
FileOptimizerPy-1.1.1641.dist-info/WHEEL
FileOptimizerPy-1.1.1641.dist-info/top_level.txt
FileOptimizerPy-1.1.1641.dist-info/RECORD
