Metadata-Version: 2.1
Name: FileOptimizerPy
Version: 1.1.1641
Summary: Python package and utility for files optimization
Home-page: https://github.com/Atronar/FileOptimizerPy
Author: ATroN
Author-email: master.atron@gmail.com
License: AGPLv3
Platform: any
Classifier: Development Status :: 5 - Production/Stable
Classifier: Operating System :: OS Independent
Classifier: License :: OSI Approved :: GNU Affero General Public License v3
Classifier: Topic :: Software Development :: Libraries :: Python Modules
Classifier: Topic :: Utilities
Classifier: Programming Language :: Python :: 3
Requires-Python: >=3.6
Requires-Dist: fleep
Requires-Dist: send2trash
Requires-Dist: jsmin
